[
    {
        "content": "<p>Has anyone worked on representation theory of finite groups over C?</p>",
        "id": 185881755,
        "sender_full_name": "Jalex Stark",
        "timestamp": 1579227392
    },
    {
        "content": "<p><span class=\"user-mention\" data-user-id=\"252300\">@Jalex Stark</span> Not that I now of. At some point <span class=\"user-mention\" data-user-id=\"220718\">@Ben McDonnell</span> worked on it a bit.</p>",
        "id": 185889922,
        "sender_full_name": "Johan Commelin",
        "timestamp": 1579240240
    },
    {
        "content": "<p>But that shouldn't stop you at all from attacking it.</p>",
        "id": 185889944,
        "sender_full_name": "Johan Commelin",
        "timestamp": 1579240321
    },
    {
        "content": "<p>Note that we would first need that basics which shouldn't be done for <em>finite</em> groups, but just in general.</p>",
        "id": 185889987,
        "sender_full_name": "Johan Commelin",
        "timestamp": 1579240344
    }
]