[
    {
        "content": "<p>Can you refer to an automatically-generated hidden assumption (like <code>h✝</code>) explicitly in a tactic somehow (e.g., so that it does what you'd naively expect <code>rw [h✝]</code> to do)? If not, is there some standard way to <em>make</em> them explicit once they already exist in the context?</p>",
        "id": 315961614,
        "sender_full_name": "Thomas Murrills",
        "timestamp": 1671081739
    },
    {
        "content": "<p>(In particular, I'm looking to refer to some of the assumptions <code>split</code> introduced.)</p>",
        "id": 315962296,
        "sender_full_name": "Thomas Murrills",
        "timestamp": 1671082427
    },
    {
        "content": "<p><code>rename_i</code> renames the last automatically introduced hygenic names.</p>",
        "id": 315962512,
        "sender_full_name": "Arien Malec",
        "timestamp": 1671082625
    },
    {
        "content": "<p>In a tactic, you should use <code>FVarId</code> to refer to hypotheses instead of user names where possible</p>",
        "id": 315962539,
        "sender_full_name": "Mario Carneiro",
        "timestamp": 1671082680
    }
]