[
    {
        "content": "<p>Hi all, I proved <a href=\"https://en.wikipedia.org/wiki/Muirhead's_inequality\">Muirhead's inequality</a> as a side project: <a href=\"https://github.com/peakpoint/muirhead\">https://github.com/peakpoint/muirhead</a></p>\n<p>I hope some of y'all find it interesting!</p>",
        "id": 320371892,
        "sender_full_name": "Tian Chen",
        "timestamp": 1673321408
    },
    {
        "content": "<p>Interesting! I have a definition of <code>majorize</code> over at <a href=\"https://github.com/leanprover-community/mathlib/tree/karamata\">branch#karamata</a></p>",
        "id": 320382122,
        "sender_full_name": "Yaël Dillies",
        "timestamp": 1673331077
    },
    {
        "content": "<p>Also I see Birkhoff's theorem in there. Have you tried using <a href=\"https://leanprover-community.github.io/mathlib_docs/find/is_extreme_point\">docs#is_extreme_point</a> and the Krein-Milman theorem (<a href=\"https://tqft.net/mathlib/analysis/convex/krein_milman\">file#analysis/convex/krein_milman</a>)?</p>",
        "id": 320382231,
        "sender_full_name": "Yaël Dillies",
        "timestamp": 1673331163
    },
    {
        "content": "<p>Will you PR it to mathlib?</p>",
        "id": 321534110,
        "sender_full_name": "Scott Morrison",
        "timestamp": 1673818913
    },
    {
        "content": "<p>I would like to see the Minkowski-Carathéodory bit extracted from the proof, which I suspect could take a while.</p>",
        "id": 321534398,
        "sender_full_name": "Yaël Dillies",
        "timestamp": 1673819113
    }
]