[
    {
        "content": "<p><span class=\"user-mention\" data-user-id=\"111080\">@Floris van Doorn</span>, I experienced a timeout with the <code>simp_nf</code> linter, at:</p>\n<p><a href=\"https://github.com/leanprover-community/mathlib/runs/987618653\">https://github.com/leanprover-community/mathlib/runs/987618653</a></p>\n<p>I don't see anything particularly evil about this lemma --- shall we just increase the timeout?</p>",
        "id": 207015933,
        "sender_full_name": "Scott Morrison",
        "timestamp": 1597487809
    },
    {
        "content": "<p>I'll look at this more carefully later. In the meantime, I'm also pinging <span class=\"user-mention\" data-user-id=\"110043\">@Gabriel Ebner</span> .</p>",
        "id": 207029011,
        "sender_full_name": "Floris van Doorn",
        "timestamp": 1597509530
    },
    {
        "content": "<p>Posted comment in PR.</p>",
        "id": 207040933,
        "sender_full_name": "Floris van Doorn",
        "timestamp": 1597528083
    }
]