[
    {
        "content": "<p>This PR now has a proof that a subgroup of a free group is itself free and is ready for review</p>",
        "id": 232884368,
        "sender_full_name": "David Wärn",
        "timestamp": 1617359503
    },
    {
        "content": "<p>This is really cool! Sorry I haven't looked at it until now. I made a few suggestions about possibly moving material earlier, but haven't actually read the proofs of the Nielsen-Schreier part.</p>",
        "id": 233163418,
        "sender_full_name": "Scott Morrison",
        "timestamp": 1617624095
    }
]