[
    {
        "content": "<p>Today I chose issue 4033 for discussion!</p>\n<p><strong><a href=\"https://github.com/leanprover-community/mathlib/issues/4033\">properties of (sub)modules</a></strong><br>\nCreated by <span class=\"user-mention\" data-user-id=\"112680\">@Johan Commelin</span> (@jcommelin) on 2020-09-03<br>\nLabels: feature-request</p>\n<p>Is this issue still relevant? Any recent updates? Anyone making progress?</p>",
        "id": 217503636,
        "sender_full_name": "Random Issue Bot",
        "timestamp": 1605968292
    },
    {
        "content": "<p>Today I chose issue 4033 for discussion!</p>\n<p><strong><a href=\"https://github.com/leanprover-community/mathlib/issues/4033\">properties of (sub)modules</a></strong><br>\nCreated by <span class=\"user-mention\" data-user-id=\"112680\">@Johan Commelin</span> (@jcommelin) on 2020-09-03<br>\nLabels: feature-request</p>\n<p>Is this issue still relevant? Any recent updates? Anyone making progress?</p>",
        "id": 234167856,
        "sender_full_name": "Random Issue Bot",
        "timestamp": 1618237494
    },
    {
        "content": "<p>flat modules are in <code>ring_theory.flat</code> and projective modules are PR'ed in <a href=\"https://github.com/leanprover-community/mathlib/issues/6813\">#6813</a> (which I just put back on the queue today).</p>",
        "id": 234171592,
        "sender_full_name": "Kevin Buzzard",
        "timestamp": 1618238768
    },
    {
        "content": "<p>Today I chose issue 4033 for discussion!</p>\n<p><strong><a href=\"https://github.com/leanprover-community/mathlib/issues/4033\">properties of (sub)modules</a></strong><br>\nCreated by <span class=\"user-mention\" data-user-id=\"112680\">@Johan Commelin</span> (@jcommelin) on 2020-09-03<br>\nLabels: feature-request</p>\n<p>Is this issue still relevant? Any recent updates? Anyone making progress?</p>",
        "id": 266505819,
        "sender_full_name": "Random Issue Bot",
        "timestamp": 1640960276
    },
    {
        "content": "<p>Today I chose issue 4033 for discussion!</p>\n<p><strong><a href=\"https://github.com/leanprover-community/mathlib/issues/4033\">properties of (sub)modules</a></strong><br>\nCreated by <span class=\"user-mention\" data-user-id=\"112680\">@Johan Commelin</span> (@jcommelin) on 2020-09-03<br>\nLabels: feature-request</p>\n<p>Is this issue still relevant? Any recent updates? Anyone making progress?</p>",
        "id": 274545821,
        "sender_full_name": "Random Issue Bot",
        "timestamp": 1646748810
    },
    {
        "content": "<p><span class=\"user-mention\" data-user-id=\"252627\">@Jujian Zhang</span> what is the status of injective modules?</p>",
        "id": 274557843,
        "sender_full_name": "Kevin Buzzard",
        "timestamp": 1646754029
    },
    {
        "content": "<p>Non-existent what so ever. We can say what is an injective object in the category of modules; but we don't have something like the following:</p>\n<div class=\"codehilite\" data-code-language=\"Lean\"><pre><span></span><code><span class=\"kd\">class</span> <span class=\"n\">module.projective</span> <span class=\"o\">(</span><span class=\"n\">R</span> <span class=\"o\">:</span> <span class=\"kt\">Type</span> <span class=\"n\">u</span><span class=\"o\">)</span> <span class=\"o\">[</span><span class=\"n\">semiring</span> <span class=\"n\">R</span><span class=\"o\">]</span> <span class=\"o\">(</span><span class=\"n\">P</span> <span class=\"o\">:</span> <span class=\"kt\">Type</span> <span class=\"o\">(</span><span class=\"n\">max</span> <span class=\"n\">u</span> <span class=\"n\">v</span><span class=\"o\">))</span> <span class=\"o\">[</span><span class=\"n\">add_comm_monoid</span> <span class=\"n\">P</span><span class=\"o\">]</span>\n  <span class=\"o\">[</span><span class=\"n\">module</span> <span class=\"n\">R</span> <span class=\"n\">P</span><span class=\"o\">]</span> <span class=\"o\">:</span> <span class=\"kt\">Prop</span> <span class=\"o\">:=</span>\n<span class=\"o\">(</span><span class=\"n\">out</span> <span class=\"o\">:</span> <span class=\"bp\">∃</span> <span class=\"n\">s</span> <span class=\"o\">:</span> <span class=\"n\">P</span> <span class=\"bp\">→ₗ</span><span class=\"o\">[</span><span class=\"n\">R</span><span class=\"o\">]</span> <span class=\"o\">(</span><span class=\"n\">P</span> <span class=\"bp\">→₀</span> <span class=\"n\">R</span><span class=\"o\">),</span> <span class=\"n\">function.left_inverse</span> <span class=\"o\">(</span><span class=\"n\">finsupp.total</span> <span class=\"n\">P</span> <span class=\"n\">P</span> <span class=\"n\">R</span> <span class=\"n\">id</span><span class=\"o\">)</span> <span class=\"n\">s</span><span class=\"o\">)</span>\n</code></pre></div>\n<p>not to mention that a module is an injective module iff it is an injective object</p>",
        "id": 274569652,
        "sender_full_name": "Jujian Zhang",
        "timestamp": 1646758524
    },
    {
        "content": "<p>I will try writing a file similar to <code>algebra/module/injective.lean</code></p>",
        "id": 274570154,
        "sender_full_name": "Jujian Zhang",
        "timestamp": 1646758723
    },
    {
        "content": "<p>There is a definition of injective module and a proof of Baer's criterion sitting at <a href=\"https://github.com/leanprover-community/mathlib/pull/12895\">#12895</a>.</p>",
        "id": 276302519,
        "sender_full_name": "Jujian Zhang",
        "timestamp": 1648025278
    },
    {
        "content": "<p>Nice!</p>",
        "id": 276311653,
        "sender_full_name": "Kevin Buzzard",
        "timestamp": 1648030698
    },
    {
        "content": "<p>Today I chose issue 4033 for discussion!</p>\n<p><strong><a href=\"https://github.com/leanprover-community/mathlib/issues/4033\">properties of (sub)modules</a></strong><br>\nCreated by <span class=\"user-mention\" data-user-id=\"112680\">@Johan Commelin</span> (@jcommelin) on 2020-09-03<br>\nLabels: feature-request</p>\n<p>Is this issue still relevant? Any recent updates? Anyone making progress?</p>",
        "id": 287437258,
        "sender_full_name": "Random Issue Bot",
        "timestamp": 1656166745
    },
    {
        "content": "<p>Today I chose issue 4033 for discussion!</p>\n<p><strong><a href=\"https://github.com/leanprover-community/mathlib/issues/4033\">properties of (sub)modules</a></strong><br>\nCreated by <span class=\"user-mention\" data-user-id=\"112680\">@Johan Commelin</span> (@jcommelin) on 2020-09-03<br>\nLabels: feature-request</p>\n<p>Is this issue still relevant? Any recent updates? Anyone making progress?</p>",
        "id": 299327434,
        "sender_full_name": "Random Issue Bot",
        "timestamp": 1663424090
    },
    {
        "content": "<p>The only remaining item on the list is \"finitely presentable\". We have this for algebras (and hence ring homs), but not yet for modules. Anyone interested in writing a small API to close this issue?</p>",
        "id": 299329943,
        "sender_full_name": "Johan Commelin",
        "timestamp": 1663425238
    },
    {
        "content": "<p>I had plans on developing some results regarding finitely presentable modules, but I won't have time until next month.</p>",
        "id": 299334076,
        "sender_full_name": "Andrew Yang",
        "timestamp": 1663427529
    },
    {
        "content": "<p>Today I chose issue 4033 for discussion!</p>\n<p><strong><a href=\"https://github.com/leanprover-community/mathlib/issues/4033\">properties of (sub)modules</a></strong><br>\nCreated by <span class=\"user-mention\" data-user-id=\"112680\">@Johan Commelin</span> (@jcommelin) on 2020-09-03<br>\nLabels: feature-request</p>\n<p>Is this issue still relevant? Any recent updates? Anyone making progress?</p>",
        "id": 303451606,
        "sender_full_name": "Random Issue Bot",
        "timestamp": 1665498876
    },
    {
        "content": "<p>Today I chose issue 4033 for discussion!</p>\n<p><strong><a href=\"https://github.com/leanprover-community/mathlib/issues/4033\">properties of (sub)modules</a></strong><br>\nCreated by <span class=\"user-mention\" data-user-id=\"112680\">@Johan Commelin</span> (@jcommelin) on 2020-09-03<br>\nLabels: feature-request</p>\n<p>Is this issue still relevant? Any recent updates? Anyone making progress?</p>",
        "id": 304969680,
        "sender_full_name": "Random Issue Bot",
        "timestamp": 1666190212
    },
    {
        "content": "<p>Today I chose issue 4033 for discussion!</p>\n<p><strong><a href=\"https://github.com/leanprover-community/mathlib/issues/4033\">properties of (sub)modules</a></strong><br>\nCreated by <span class=\"user-mention\" data-user-id=\"112680\">@Johan Commelin</span> (@jcommelin) on 2020-09-03<br>\nLabels: feature-request</p>\n<p>Is this issue still relevant? Any recent updates? Anyone making progress?</p>",
        "id": 307122218,
        "sender_full_name": "Random Issue Bot",
        "timestamp": 1667226590
    },
    {
        "content": "<p>Today I chose issue 4033 for discussion!</p>\n<p><strong><a href=\"https://github.com/leanprover-community/mathlib/issues/4033\">properties of (sub)modules</a></strong><br>\nCreated by <span class=\"user-mention\" data-user-id=\"112680\">@Johan Commelin</span> (@jcommelin) on 2020-09-03<br>\nLabels: feature-request</p>\n<p>Is this issue still relevant? Any recent updates? Anyone making progress?</p>",
        "id": 309344483,
        "sender_full_name": "Random Issue Bot",
        "timestamp": 1668262045
    },
    {
        "content": "<p>Today I chose issue 4033 for discussion!</p>\n<p><strong><a href=\"https://github.com/leanprover-community/mathlib/issues/4033\">properties of (sub)modules</a></strong><br>\nCreated by <span class=\"user-mention\" data-user-id=\"112680\">@Johan Commelin</span> (@jcommelin) on 2020-09-03<br>\nLabels: feature-request</p>\n<p>Is this issue still relevant? Any recent updates? Anyone making progress?</p>",
        "id": 317574829,
        "sender_full_name": "Random Issue Bot",
        "timestamp": 1671804543
    }
]