[
    {
        "content": "<p>Today I chose PR 13500 for discussion!</p>\n<p><strong><a href=\"https://github.com/leanprover-community/mathlib/issues/13500\">uniform_limit_of_holo_is_holo</a></strong><br>\nCreated by <span class=\"user-mention\" data-user-id=\"389019\">@Chris Birkbeck</span> (@CBirkbeck) on 2022-04-18<br>\nLabels: WIP</p>\n<p>Is this PR still relevant? Any recent updates? Anyone making progress?</p>",
        "id": 321170316,
        "sender_full_name": "Random Issue Bot",
        "timestamp": 1673618974
    },
    {
        "content": "<p>No its been replaced by <a href=\"https://github.com/leanprover-community/mathlib/pull/17074\">#17074</a> (at least the final result, other bits may still appear in mathlib, but separately)</p>",
        "id": 321170794,
        "sender_full_name": "Chris Birkbeck",
        "timestamp": 1673619114
    },
    {
        "content": "<p>Can we close it?</p>",
        "id": 321171435,
        "sender_full_name": "Riccardo Brasca",
        "timestamp": 1673619264
    },
    {
        "content": "<p>yep!</p>",
        "id": 321175349,
        "sender_full_name": "Chris Birkbeck",
        "timestamp": 1673620221
    }
]