[
    {
        "content": "<p>Is there any reason to have a special name <a href=\"https://leanprover-community.github.io/mathlib_docs/find/finset.erase\">docs#finset.erase</a> for <code>s \\ {a}</code>?</p>",
        "id": 256749838,
        "sender_full_name": "Yury G. Kudryashov",
        "timestamp": 1633703987
    },
    {
        "content": "<p>For definitional equality with <code>multiset.erase</code>and <code>list.erase</code>?</p>",
        "id": 256751204,
        "sender_full_name": "Eric Wieser",
        "timestamp": 1633704532
    }
]