[
    {
        "content": "<p>I am trying to create an <code>all.lean</code> so that I can run linters locally. <del><code>leanproject mk-all</code> seems to be a no-op.</del>  (the file is <code>src/all.lean</code>, but not made if <code>src/all.lean</code> exists, iiuc). What's the right approach here?</p>",
        "id": 258960743,
        "sender_full_name": "Yakov Pechersky",
        "timestamp": 1635169477
    },
    {
        "content": "<p>run <code>scripts/mk_all.sh</code></p>",
        "id": 258962735,
        "sender_full_name": "Floris van Doorn",
        "timestamp": 1635170324
    }
]