[
    {
        "content": "<p>When does VSCode use outdated oleans? I've heard that sometimes if you edit a file deep in the import hierarchy, VSCode will just give up and use the outdated oleans.</p>",
        "id": 202721376,
        "sender_full_name": "Kenny Lau",
        "timestamp": 1593711859
    },
    {
        "content": "<p>You are not talking about the <code>--old</code> command line option to Lean, or is that what you meant?</p>",
        "id": 202721689,
        "sender_full_name": "Johan Commelin",
        "timestamp": 1593712018
    },
    {
        "content": "<p>no, I'm not talking about <code>--old</code></p>",
        "id": 202726224,
        "sender_full_name": "Kenny Lau",
        "timestamp": 1593714070
    }
]