[
    {
        "content": "<p>Having typeclasses and defs in namespaces (as opposed to just lemmas), as is done in category theory, ends up giving us some stupid names, like <a href=\"https://leanprover-community.github.io/mathlib_docs/find/category_theory.bundled_hom.category_theory.bundled.category_theory.concrete_category\">docs#category_theory.bundled_hom.category_theory.bundled.category_theory.concrete_category</a></p>\n<p>Could we make it so that instances only get the namespace once?</p>",
        "id": 269463721,
        "sender_full_name": "Yaël Dillies",
        "timestamp": 1643223727
    },
    {
        "content": "<p>can you even type that without the linter having a fit?</p>",
        "id": 269463840,
        "sender_full_name": "Eric Rodriguez",
        "timestamp": 1643223772
    },
    {
        "content": "<p>Just about! It's 86 characters long.</p>",
        "id": 269463927,
        "sender_full_name": "Yaël Dillies",
        "timestamp": 1643223798
    }
]