[
    {
        "content": "<p>when I type <code>#check foo</code>:<br>\n<a href=\"/user_uploads/3121/vlu3_o-aXD_2lFd7oBQItH6f/2020-05-23-1.png\">/user_uploads/3121/vlu3_o-aXD_2lFd7oBQItH6f/2020-05-23-1.png</a> </p>\n<div class=\"message_inline_image\"><a href=\"/user_uploads/3121/vlu3_o-aXD_2lFd7oBQItH6f/2020-05-23-1.png\"><img src=\"/user_uploads/3121/vlu3_o-aXD_2lFd7oBQItH6f/2020-05-23-1.png\"></a></div><p>when I click elsewhere and return to that cursor position and press Ctrl+Space:<br>\n<a href=\"/user_uploads/3121/IGw15O6PIRpDZMsGaaKqayFr/2020-05-23-2.png\">/user_uploads/3121/IGw15O6PIRpDZMsGaaKqayFr/2020-05-23-2.png</a></p>\n<div class=\"message_inline_image\"><a href=\"/user_uploads/3121/IGw15O6PIRpDZMsGaaKqayFr/2020-05-23-2.png\"><img src=\"/user_uploads/3121/IGw15O6PIRpDZMsGaaKqayFr/2020-05-23-2.png\"></a></div>",
        "id": 198535713,
        "sender_full_name": "Kenny Lau",
        "timestamp": 1590240457
    },
    {
        "content": "<p>so the issue is that when I press Ctrl+Space, some suggestions (such as <code>foo.bar</code>) are missing</p>",
        "id": 198535753,
        "sender_full_name": "Kenny Lau",
        "timestamp": 1590240482
    },
    {
        "content": "<p>the opposite situation occurs if I type <code>#check bar</code>: the first time it doesn't come up, but it comes up on Ctrl+Space</p>",
        "id": 198535776,
        "sender_full_name": "Kenny Lau",
        "timestamp": 1590240518
    },
    {
        "content": "<p>and for <code>insert_emptyc_eq</code>, it neither shows up in the first time nor by Ctrl+Space</p>",
        "id": 198535844,
        "sender_full_name": "Kenny Lau",
        "timestamp": 1590240610
    },
    {
        "content": "<p>This randomness has been there since the start and I would love to understand it better</p>",
        "id": 198538598,
        "sender_full_name": "Kevin Buzzard",
        "timestamp": 1590245237
    }
]