[
    {
        "content": "<div class=\"message_inline_image\"><a href=\"https://imgs.xkcd.com/comics/voting_software.png\" target=\"_blank\" title=\"https://imgs.xkcd.com/comics/voting_software.png\"><img src=\"https://imgs.xkcd.com/comics/voting_software.png\"></a></div>",
        "id": 187371697,
        "sender_full_name": "Tim Daly",
        "timestamp": 1580832417
    },
    {
        "content": "<p>That's why we need Lean</p>",
        "id": 187371718,
        "sender_full_name": "Tim Daly",
        "timestamp": 1580832433
    }
]