[
    {
        "content": "<p>Dear All,</p>\n<p>I am not registered to the conference, but I was wondering if it was possible nonetheless to have access to the live videos for the rest of the week.</p>\n<p>If it is not possible, then I'll just wait for the recordings!</p>\n<p>Thank you very much!</p>",
        "id": 289384675,
        "sender_full_name": "Damiano Testa",
        "timestamp": 1657659595
    },
    {
        "content": "<p>just DM'd you</p>",
        "id": 289417193,
        "sender_full_name": "Junyan Xu",
        "timestamp": 1657690147
    }
]