[
    {
        "content": "<p>If I understand correctly then <code>[has_scalar α α]</code> implies <code>[has_mul α]</code> but I cannot find it as <code>extends</code> in the definition. How does it work?</p>",
        "id": 268017403,
        "sender_full_name": "Martin Dvořák",
        "timestamp": 1642169096
    },
    {
        "content": "<p>It's the other way around. <code>has_mul α</code> implies <code>has_scalar α α</code> thanks to <a href=\"https://leanprover-community.github.io/mathlib_docs/find/has_mul.to_has_scalar\">docs#has_mul.to_has_scalar</a>. They are different things so nothing in common on the definition level.</p>",
        "id": 268017894,
        "sender_full_name": "Yaël Dillies",
        "timestamp": 1642169325
    },
    {
        "content": "<p><span class=\"user-mention silent\" data-user-id=\"417654\">Martin Dvořák</span> has marked this topic as resolved.</p>",
        "id": 268018023,
        "sender_full_name": "Notification Bot",
        "timestamp": 1642169390
    }
]