[
    {
        "content": "<p>I think the major premise becomes <code>h : is_nilpotent G</code> with my suggestion</p>",
        "id": 268874734,
        "sender_full_name": "Eric Wieser",
        "timestamp": 1642786077
    },
    {
        "content": "<p>You might need to tag the lemma with elab_as_elim so that the elaboration strategy is different, that might make it work better with induction</p>",
        "id": 268874812,
        "sender_full_name": "Yakov Pechersky",
        "timestamp": 1642786096
    },
    {
        "content": "<p>Thanks, but still can’t get it to work</p>",
        "id": 268876469,
        "sender_full_name": "Joachim Breitner",
        "timestamp": 1642786810
    },
    {
        "content": "<p>Oh, now I can! Indeed, induction on <code>is_nilpotent</code> helps.</p>",
        "id": 268876607,
        "sender_full_name": "Joachim Breitner",
        "timestamp": 1642786877
    },
    {
        "content": "<p><span class=\"user-mention silent\" data-user-id=\"470149\">Joachim Breitner</span> has marked this topic as resolved.</p>",
        "id": 268877430,
        "sender_full_name": "Notification Bot",
        "timestamp": 1642787239
    },
    {
        "content": "<p>So <code>induction h using nilpotent_center_quotient_ind</code> works in your PR?</p>",
        "id": 268888008,
        "sender_full_name": "Eric Wieser",
        "timestamp": 1642791528
    },
    {
        "content": "<p>Yes</p>",
        "id": 268888070,
        "sender_full_name": "Joachim Breitner",
        "timestamp": 1642791556
    },
    {
        "content": "<p><a href=\"https://github.com/leanprover-community/mathlib/pull/11586/files#diff-d9b6fae55b9ea896727c9ac262142c4b401d53bb1c10a8f775eac21a56a29013R723\">https://github.com/leanprover-community/mathlib/pull/11586/files#diff-d9b6fae55b9ea896727c9ac262142c4b401d53bb1c10a8f775eac21a56a29013R723</a><br>\n(That PR is low on the reviewing stack, don’t look too closely, I will clean it up more once the others are in and I learned more :-))</p>",
        "id": 268888134,
        "sender_full_name": "Joachim Breitner",
        "timestamp": 1642791582
    }
]