[
    {
        "content": "<p>I was suprised to see I could define <code>def foo (b0: bool) (b1: bool) : bool  := b0 = b1</code> directly. Looks like there is a type classe mechanism <code>decidable_eq</code> behind that, am I right ?</p>",
        "id": 177510574,
        "sender_full_name": "Vincent Siles",
        "timestamp": 1570448069
    },
    {
        "content": "<p>Indeed. You can see how that gets elaborated with</p>\n<div class=\"codehilite\"><pre><span></span><span class=\"kn\">set_option</span> <span class=\"n\">pp</span><span class=\"bp\">.</span><span class=\"n\">implicit</span> <span class=\"n\">true</span>\n<span class=\"bp\">#</span><span class=\"kn\">print</span> <span class=\"n\">foo</span>\n</pre></div>",
        "id": 177510846,
        "sender_full_name": "Rob Lewis",
        "timestamp": 1570448335
    },
    {
        "content": "<p>Thank you !</p>",
        "id": 177511013,
        "sender_full_name": "Vincent Siles",
        "timestamp": 1570448485
    }
]