[
    {
        "content": "<p>hi, i m new here.</p>",
        "id": 220936373,
        "sender_full_name": "greatRay",
        "timestamp": 1608930779
    },
    {
        "content": "<p>This topic was moved here from <a class=\"stream-topic\" data-stream-id=\"113488\" href=\"/#narrow/stream/113488-general/topic/options.20in.20user.20attributes\">#general &gt; options in user attributes</a> by <span class=\"user-mention silent\" data-user-id=\"123965\">Bryan Gin-ge Chen</span></p>",
        "id": 220936836,
        "sender_full_name": "Notification Bot",
        "timestamp": 1608931576
    },
    {
        "content": "<p>Welcome! I've moved your message to your own thread. Feel free to ask any questions about Lean in separate threads in <a class=\"stream\" data-stream-id=\"113489\" href=\"/#narrow/stream/113489-new-members\">#new members</a> !</p>",
        "id": 220936859,
        "sender_full_name": "Bryan Gin-ge Chen",
        "timestamp": 1608931658
    }
]