[
    {
        "content": "<p>When I opened my computer today, VSCode decided to show me an \"infoview\" window with a lot of messages instead of one single goal, and I was wondering if there were a way to go back to a single message with just the current goal</p>",
        "id": 203367253,
        "sender_full_name": "Nicolò Cavalleri",
        "timestamp": 1594287532
    },
    {
        "content": "<p>Can't you fold away the \"all messages\"?</p>",
        "id": 203367555,
        "sender_full_name": "Kevin Buzzard",
        "timestamp": 1594287739
    },
    {
        "content": "<p>But then I get nothing! Maybe I lost the tactic state</p>",
        "id": 203367700,
        "sender_full_name": "Nicolò Cavalleri",
        "timestamp": 1594287870
    },
    {
        "content": "<p>The new infoview should be doubling up as both the old views. Put your cursor in the middle of a tactic mode proof to see it in action</p>",
        "id": 203367754,
        "sender_full_name": "Kevin Buzzard",
        "timestamp": 1594287912
    },
    {
        "content": "<p><span class=\"user-mention silent\" data-user-id=\"110038\">Kevin Buzzard</span> <a href=\"#narrow/stream/113489-new-members/topic/infoview.20vs.20goal/near/203367754\">said</a>:</p>\n<blockquote>\n<p>The new infoview should be doubling up as both the old views. Put your cursor in the middle of a tactic mode proof to see it in action</p>\n</blockquote>\n<p>I was doing it but something weird is happening: if I only click in the middle of a proof nothing shows up, but if I write something then the tactic state appears... It is weird because I remembered that until yesterday the window was different and I only had a simple goal without all messages or anything like that, but maybe I remember wrong</p>",
        "id": 203368093,
        "sender_full_name": "Nicolò Cavalleri",
        "timestamp": 1594288176
    },
    {
        "content": "<p>But at least now I found a way to get the tactic state back</p>",
        "id": 203368160,
        "sender_full_name": "Nicolò Cavalleri",
        "timestamp": 1594288205
    },
    {
        "content": "<p>Yesterday you couldn't click on something in the goal window and see its type. This is the big win</p>",
        "id": 203368181,
        "sender_full_name": "Kevin Buzzard",
        "timestamp": 1594288224
    },
    {
        "content": "<p>So was something updated yesterday? I did not update anything manually!</p>",
        "id": 203368325,
        "sender_full_name": "Nicolò Cavalleri",
        "timestamp": 1594288352
    },
    {
        "content": "<p>Are you sure you did not type <code>leanproject up</code>?</p>",
        "id": 203368944,
        "sender_full_name": "Johan Commelin",
        "timestamp": 1594288829
    },
    {
        "content": "<p>What is the content of your <code>leanpkg.toml</code>?</p>",
        "id": 203368951,
        "sender_full_name": "Johan Commelin",
        "timestamp": 1594288840
    },
    {
        "content": "<p>Note that VS Code might have auto-updated the lean extension. (But you need both a new version of lean, and a new version of the VS Code lean extension.)</p>",
        "id": 203368982,
        "sender_full_name": "Johan Commelin",
        "timestamp": 1594288872
    }
]