[
    {
        "content": "<p>I can't help but notice its only had two contributors and was last touched last year.</p>\n<p>Is there an alternative?</p>",
        "id": 175185299,
        "sender_full_name": "Robert Spencer",
        "timestamp": 1567950447
    },
    {
        "content": "<p>Most of the time people just make pull requests against mathlib when they're ready nowadays</p>",
        "id": 175190690,
        "sender_full_name": "Keeley Hoek",
        "timestamp": 1567960031
    }
]