[
    {
        "content": "<p><span class=\"user-mention silent\" data-user-id=\"463310\">Greg Leo</span> <a href=\"#narrow/stream/113489-new-members/topic/Unknown.20Identifier.20transR/near/264914087\">said</a>:</p>\n<blockquote>\n<p>In VS code, sometimes my ability to peek at definitions just goes away. Is this a known bug?</p>\n</blockquote>\n<p>I think it deserves a thread of its own, but I'm going to say something related:<br>\nIn Lean 3 I remember being able to ctrl+click on imports and it would take me to the respective modules. But I'm not able to do it in Lean 4 anymore <span aria-label=\"sad\" class=\"emoji emoji-2639\" role=\"img\" title=\"sad\">:sad:</span><br>\n(can a mod split this thread in two please? <span aria-label=\"pray\" class=\"emoji emoji-1f64f\" role=\"img\" title=\"pray\">:pray:</span> )</p>",
        "id": 264918971,
        "sender_full_name": "Arthur Paulino",
        "timestamp": 1639512991
    },
    {
        "content": "<p>In Lean4, are the cases it doesn't work for you stdlib modules perchance?</p>",
        "id": 264929471,
        "sender_full_name": "Julian Berman",
        "timestamp": 1639517998
    },
    {
        "content": "<p>Er, core modules I suppose I mean.</p>",
        "id": 264929563,
        "sender_full_name": "Julian Berman",
        "timestamp": 1639518010
    },
    {
        "content": "<p>It doesn't work for any import right now (modules inside the package nor from core (<code>Prelude.lean</code> for instance))</p>",
        "id": 264931071,
        "sender_full_name": "Arthur Paulino",
        "timestamp": 1639518570
    },
    {
        "content": "<p><span class=\"user-mention silent\" data-user-id=\"463310\">Greg Leo</span> <a href=\"#narrow/stream/113489-new-members/topic/peek.20definition.20sometimes.20fails.20in.20VS.20code/near/264914087\">said</a>:</p>\n<blockquote>\n<p>In VS code, sometimes my ability to peek at definitions just goes away. Is this a known bug?</p>\n</blockquote>\n<p>Is there any pattern to when this is happening?  In particular, is this happening when you have an error in your code?  Or when the orange progress bar hasn't made (enough) progress yet?</p>",
        "id": 265128562,
        "sender_full_name": "Stuart Presnell",
        "timestamp": 1639646150
    }
]